{
    "$schema": "http://json-schema.org/draft-07/schema#",
    "title": "Catalyst Fund 14 Base Proposal Template",
    "description": "A structured template for creating Fund 14 proposals",
    "type": "object",
    "properties": {
        "$schema": "./.schema.json",
        "template_version": {
            "type": "object",
            "properties": {
                "uid": {
                    "const": "version_section",
                    "description": "Unique identifier for the version."
                },
                "title": {
                    "const": "Version",
                    "description": "Title of the version."
                },
                "description": {
                    "const": "The version of the schema, formatted as a ULID.",
                    "description": "Description for the version."
                },
                "value": {
                    "type": "string",
                    "description": "A unique identifier for the version, formatted as a ULID.",
                    "pattern": "^[0-9A-HJKMNP-TV-Z]{26}$",
                    "default": "01F8MECHZXK8F8D8F8D8F8D8F8"
                }
            },
            "required": ["uid", "title", "description", "value"]
        },
        "category_template": {
            "type": "object",
            "properties": {
                "uid": {
                    "const": "category_section",
                    "description": "Unique identifier for the category."
                },
                "title": {
                    "const": "Category",
                    "description": "Title of the category."
                },
                "description": {
                    "const": "The category to which this template belongs.",
                    "description": "Description for the category."
                },
                "value": {
                    "type": "string",
                    "description": "A unique identifier for the category.",
                    "pattern": "^[a-zA-Z0-9_-]+$",
                    "default": "cardano_open_category"
                }
            },
            "required": ["uid", "title", "description", "value"]
        },
        "proposal_setup_segment": {
            "type": "object",
            "properties": {
                "uid": {
                    "const": "proposal_setup_section",
                    "description": "Unique identifier for the Proposal Setup Segment."
                },
                "title": {
                    "const": "Proposal Setup",
                    "description": "Title of the Proposal Setup Segment."
                },
                "description": {
                    "const": "Basic information about your proposal.",
                    "description": "Description for the Proposal Setup Segment."
                },
                "value": {
                    "type": "object",
                    "properties": {
                        "proposal_title": {
                            "type": "object",
                            "properties": {
                                "uid": {
                                    "const": "proposal_title_field_section",
                                    "description": "Unique identifier for the Proposal Title field."
                                },
                                "title": {
                                    "const": "Proposal Title",
                                    "description": "Title of the Proposal Title field."
                                },
                                "description": {
                                    "const": "The name of the proposal.",
                                    "description": "Description for the Proposal Title field."
                                },
                                "value": {
                                    "type": "string",
                                    "maxLength": 60,
                                    "description": "User-provided proposal title.",
                                    "format": "string",
                                    "pattern": "^[a-zA-Z0-9 ]+$"
                                }
                            },
                            "required": ["uid", "title", "description", "value"]
                        }
                    }
                }
            },
            "required": ["uid", "title", "description", "value"]
        },
        "proposal_summary_segment": {
            "type": "object",
            "properties": {
                "uid": {
                    "const": "proposal_details_section",
                    "description": "Unique identifier for the Proposal Details."
                },
                "title": {
                    "const": "Proposal Details",
                    "description": "Details about the proposal."
                },
                "description": {
                    "const": "Detailed information about the proposal.",
                    "description": "Description for the Proposal Details."
                },
                "value": {
                    "type": "object",
                    "properties": {
                        "proposal_problem": {
                            "type": "string",
                            "description": "Describe the problem you're addressing in the Cardano ecosystem.",
                            "maxLength": 1000,
                            "format": "string",
                            "pattern": "^[\\s\\S]*$"
                        },
                        "proposal_solution": {
                            "type": "string",
                            "description": "Describe your solution and how it addresses the problem.",
                            "maxLength": 2000,
                            "format": "string",
                            "pattern": "^[\\s\\S]*$"
                        }
                    },
                    "required": ["proposal_problem", "proposal_solution"]
                }
            },
            "required": ["uid", "title", "description", "value"]
        },
        "public_description_segment": {
            "type": "object",
            "properties": {
                "uid": {
                    "const": "public_description_section",
                    "description": "Unique identifier for the Public Description Segment."
                },
                "title": {
                    "const": "Public Description",
                    "description": "Public description of the proposal."
                },
                "description": {
                    "const": "Detailed public description information.",
                    "description": "Description for the Public Description Segment."
                },
                "value": {
                    "type": "object",
                    "properties": {
                        "topic_1": {
                            "type": "string",
                            "description": "First topic of the public description.",
                            "maxLength": 500,
                            "format": "string",
                            "pattern": "^[a-zA-Z0-9 ]+$"
                        },
                        "topic_2": {
                            "type": "string",
                            "description": "Second topic of the public description.",
                            "maxLength": 500,
                            "format": "string",
                            "pattern": "^[a-zA-Z0-9 ]+$"
                        },
                        "topic_3": {
                            "type": "string",
                            "description": "Third topic of the public description.",
                            "maxLength": 500,
                            "format": "string",
                            "pattern": "^[a-zA-Z0-9 ]+$"
                        },
                        "topic_4": {
                            "type": "string",
                            "description": "Fourth topic of the public description.",
                            "maxLength": 500,
                            "format": "string",
                            "pattern": "^[a-zA-Z0-9 ]+$"
                        }
                    },
                    "required": ["topic_1", "topic_2", "topic_3", "topic_4"]
                }
            },
            "required": ["uid", "title", "description", "value"]
        },
        "category_segment": {
            "type": "object",
            "properties": {
                "uid": {
                    "const": "category_segment_section",
                    "description": "Unique identifier for the Category Segment."
                },
                "title": {
                    "const": "Category Segment",
                    "description": "Segment for categorizing the proposal."
                },
                "description": {
                    "const": "Details about the categories related to the proposal.",
                    "description": "Description for the Category Segment."
                },
                "value": {
                    "type": "object",
                    "properties": {
                        "additional_questions": {
                            "type": "object",
                            "properties": {
                                "uid": {
                                    "const": "additional_questions_section",
                                    "description": "Unique identifier for Additional Questions."
                                },
                                "title": {
                                    "const": "Additional Questions",
                                    "description": "Questions related to the project."
                                },
                                "description": {
                                    "const": "Details about additional questions regarding the project.",
                                    "description": "Description for Additional Questions."
                                },
                                "value": {
                                    "type": "object",
                                    "properties": {
                                        "is_open_source": {
                                            "type": "boolean",
                                            "description": "Is the project open source?"
                                        },
                                        "license_type": {
                                            "type": "string",
                                            "description": "Type of license used.",
                                            "format": "string",
                                            "pattern": "^[a-zA-Z0-9 ]+$"
                                        },
                                        "product_repository_url": {
                                            "type": "string",
                                            "format": "uri",
                                            "description": "URL to the product repository."
                                        },
                                        "project_documentation_url": {
                                            "type": "string",
                                            "format": "uri",
                                            "description": "URL to project documentation."
                                        }
                                    },
                                    "required": ["is_open_source", "license_type", "product_repository_url", "project_documentation_url"]
                                }
                            },
                            "required": ["uid", "title", "description", "value"]
                        },
                        "milestones": {
                            "type": "object",
                            "properties": {
                                "uid": {
                                    "const": "milestones_section",
                                    "description": "Unique identifier for the Project Milestones."
                                },
                                "title": {
                                    "const": "Project Milestones",
                                    "description": "Milestones for the project."
                                },
                                "description": {
                                    "const": "Milestones to track project progress.",
                                    "description": "Description for the Project Milestones."
                                },
                                "value": {
                                    "type": "array",
                                    "items": {
                                        "type": "object",
                                        "properties": {
                                            "title": {
                                                "type": "string",
                                                "description": "Milestone Title.",
                                                "maxLength": 100,
                                                "format": "string",
                                                "pattern": "^[a-zA-Z0-9 ]+$"
                                            },
                                            "description": {
                                                "type": "string",
                                                "description": "Milestone Description.",
                                                "maxLength": 500,
                                                "format": "string",
                                                "pattern": "^[\\s\\S]*$" 
                                            },
                                            "deliverables": {
                                                "type": "array",
                                                "items": {
                                                    "type": "string",
                                                    "format": "string",
                                                    "pattern": "^[a-zA-Z0-9 ]+$"
                                                }
                                            }
                                        },
                                        "required": ["title", "description", "deliverables"]
                                    }
                                }
                            },
                            "required": ["uid", "title", "description", "value"]
                        },
                        "resources": {
                            "type": "object",
                            "properties": {
                                "uid": {
                                    "const": "resources_section",
                                    "description": "Unique identifier for Resources and Budget."
                                },
                                "title": {
                                    "const": "Resources and Budget",
                                    "description": "Details about resources and budget."
                                },
                                "description": {
                                    "const": "Information about resources and budget allocation.",
                                    "description": "Description for Resources and Budget."
                                },
                                "value": {
                                    "type": "object",
                                    "properties": {
                                        "project_team": {
                                            "type": "array",
                                            "items": {
                                                "type": "object",
                                                "properties": {
                                                    "role": {
                                                        "type": "string",
                                                        "description": "Role of the team member.",
                                                        "maxLength": 100,
                                                        "format": "string",
                                                        "pattern": "^[a-zA-Z0-9 ]+$"
                                                    },
                                                    "experience": {
                                                        "type": "string",
                                                        "description": "Relevant experience of the team member.",
                                                        "maxLength": 500,
                                                        "format": "string",
                                                        "pattern": "^[\\s\\S]*$" 
                                                    }
                                                },
                                                "required": ["role", "experience"]
                                            }
                                        },
                                        "budget_breakdown": {
                                            "type": "string",
                                            "description": "Detailed breakdown of how the funds will be used.",
                                            "maxLength": 2000,
                                            "format": "string",
                                            "pattern": "^[\\s\\S]*$" 
                                        }
                                    },
                                    "required": ["project_team", "budget_breakdown"]
                                }
                            },
                            "required": ["uid", "title", "description", "value"]
                        },
                        "agreements": {
                            "type": "object",
                            "properties": {
                                "uid": {
                                    "const": "agreements_section",
                                    "description": "Unique identifier for Terms and Agreements."
                                },
                                "title": {
                                    "const": "Terms and Agreements",
                                    "description": "Agreements related to the proposal."
                                },
                                "description": {
                                    "const": "Terms and agreements for the proposal.",
                                    "description": "Description for Terms and Agreements."
                                },
                                "value": {
                                    "type": "object",
                                    "properties": {
                                        "agree_fund_rules": {
                                            "type": "boolean",
                                            "description": "Agreement to fund rules."
                                        },
                                        "catalyst_terms_and_conditions": {
                                            "type": "boolean",
                                            "description": "Agreement to terms and conditions."
                                        },
                                        "privacy_policy": {
                                            "type": "boolean",
                                            "description": "Agreement to privacy policy."
                                        }
                                    },
                                    "required": ["agree_fund_rules", "catalyst_terms_and_conditions", "privacy_policy"]
                                }
                            },
                            "required": ["uid", "title", "description", "value"]
                        }
                    },
                    "required": ["additional_questions", "milestones", "resources", "agreements"]
                }
            },
            "required": ["uid", "title", "description", "value"]
        }
    }
}